avalpdf/__init__.py
avalpdf/cli.py
avalpdf/converter.py
avalpdf/extractor.py
avalpdf/formatter.py
avalpdf/rich_formatter.py
avalpdf/utils.py
avalpdf/validator.py
avalpdf/version.py
avalpdf-0.1.8.dist-info/METADATA
avalpdf-0.1.8.dist-info/WHEEL
avalpdf-0.1.8.dist-info/entry_points.txt
avalpdf-0.1.8.dist-info/top_level.txt
avalpdf-0.1.8.dist-info/RECORD
